yt_dlp_plugins/extractor/getpot_wpc.py
yt_dlp_getpot_wpc-1.0.0.dist-info/METADATA
yt_dlp_getpot_wpc-1.0.0.dist-info/WHEEL
yt_dlp_getpot_wpc-1.0.0.dist-info/licenses/LICENSE
yt_dlp_getpot_wpc-1.0.0.dist-info/RECORD
