Metadata-Version: 2.4
Name: yt-dlp-getpot-wpc
Version: 1.0.0
Author-email: coletdjnz <coletdjnz@protonmail.com>
License: MIT License
License-File: LICENSE
Keywords: yt-dlp,yt-dlp-plugin,yt-dlp-pot-provider
Requires-Python: >=3.9
Requires-Dist: nodriver
